pywxdump_mini/__init__.py
pywxdump_mini/simplify_wx_info.py
pywxdump_sample-1.1.0.dist-info/LICENSE
pywxdump_sample-1.1.0.dist-info/METADATA
pywxdump_sample-1.1.0.dist-info/WHEEL
pywxdump_sample-1.1.0.dist-info/entry_points.txt
pywxdump_sample-1.1.0.dist-info/top_level.txt
pywxdump_sample-1.1.0.dist-info/RECORD
