Metadata-Version: 2.1
Name: pywxdump-sample
Version: 1.1.0
Summary: 微信信息获取工具
Home-page: https://github.com/zezezez/pywxdump_sample/
Author: 
Author-email: 
License: MIT
Classifier: Programming Language :: Python :: 3
Classifier: Operating System :: OS Independent
Requires-Python: >=3.6, <4
License-File: LICENSE
Requires-Dist: pymem
Requires-Dist: psutil
